{
  "client": [
    {
      "services": {
        "appinvite_service": {
          "status": 1
        }, 
        "analytics_service": {
          "status": 0
        }
      }, 
      "oauth_client": [
        {
          "client_id": "433971752222-ccn7hlgoqiup7lk8baeusoshrj65m5em.apps.googleusercontent.com"
        }
      ], 
      "api_key": [
        {
          "current_key": "AIzaSyCGAu2qM1cShd2JBAOPXfiu4Br_D3jXDIg"
        }
      ], 
      "client_info": {
        "mobilesdk_app_id": "1:433971752222:ios:22c4c311ab464802de6d0f", 
        "android_client_info": {
          "package_name": "com.JWCTwenyTwenty.CanYouCount"
        }
      }
    }
  ], 
  "configuration_version": "1", 
  "project_info": {
    "storage_bucket": "canyoucount2020-1234.appspot.com", 
    "project_id": "canyoucount2020-1234", 
    "firebase_url": "https://canyoucount2020-1234.firebaseio.com", 
    "project_number": "433971752222"
  }
}